ipgeo_mmdb_reader/__init__.py
ipgeo_mmdb_reader/errors.py
ipgeo_mmdb_reader/py.typed
ipgeo_mmdb_reader/reader.py
ipgeo_mmdb_reader/utils.py
ipgeolocation_mmdb_reader-1.0.0.dist-info/METADATA
ipgeolocation_mmdb_reader-1.0.0.dist-info/WHEEL
ipgeolocation_mmdb_reader-1.0.0.dist-info/licenses/LICENSE
ipgeolocation_mmdb_reader-1.0.0.dist-info/RECORD
