Metadata-Version: 2.4
Name: ipgeolocation-mmdb-reader
Version: 1.0.0
Summary: IPGeolocation MMDB Reader
Project-URL: Homepage, https://ipgeolocation.io/
Project-URL: Repository, https://git.jfreaks.com/IPGeolocation/mmdb-reader
Project-URL: Issues, https://git.jfreaks.com/IPGeolocation/mmdb-reader/issues
Author-email: "ipgeolocation.io" <support@ipgeolocation.io>
License: MIT License
License-File: LICENSE
Classifier: Development Status :: 5 - Production/Stable
Classifier: Intended Audience :: Developers
Classifier: License :: OSI Approved :: MIT License
Classifier: Programming Language :: Python
Classifier: Programming Language :: Python :: 3
Classifier: Programming Language :: Python :: 3.9
Classifier: Programming Language :: Python :: 3.10
Classifier: Programming Language :: Python :: 3.11
Classifier: Programming Language :: Python :: 3.12
Classifier: Programming Language :: Python :: 3.13
Classifier: Topic :: Database
Classifier: Topic :: Internet
Classifier: Typing :: Typed
Requires-Python: >=3.9
